arelai/environment.py
arelai/game.py
arelai/player.py
arelai-0.0.7.dist-info/licenses/LICENSE.txt
arelai-0.0.7.dist-info/METADATA
arelai-0.0.7.dist-info/WHEEL
arelai-0.0.7.dist-info/top_level.txt
arelai-0.0.7.dist-info/RECORD
