Metadata-Version: 2.4
Name: arelai
Version: 0.0.7
Summary: A library for creating games and training agents using reinforcement learning.
Author-email: Chandra Gummaluru <chandra.gummaluru@gmail.com>
Project-URL: Homepage, https://github.com/chandra-gummaluru/arelai
Project-URL: Issues, https://github.com/chandra-gummaluru/arelai/issues
Classifier: Programming Language :: Python :: 3
Classifier: Operating System :: OS Independent
Classifier: License :: OSI Approved :: MIT License
Requires-Python: >=3.8
License-File: LICENSE.txt
Dynamic: license-file
